hack4u/__init__.py
hack4u/courses.py
hack4u/utils.py
HHack4u-0.7.7.dist-info/METADATA
HHack4u-0.7.7.dist-info/WHEEL
HHack4u-0.7.7.dist-info/top_level.txt
HHack4u-0.7.7.dist-info/RECORD
