Metadata-Version: 2.1
Name: HHack4u
Version: 0.7.7
Summary: Una biblioteca para consultar cursos de hack4u.
Home-page: https://hack4u.io
Author: carlos
